{"Model X AWD - P100D": ["2016", "2017"], "Model X 100D": ["2018", "2019"], "Model S AWD - P90D": ["2015", "2016", "2017"], "Model S 100D": ["2018", "2019"], "Model S AWD - 60D": ["2016", "2017"], "Model S AWD (85 kW-hr battery pack)": ["2014"], "Model X 75D": ["2018", "2019"], "Model S AWD - P100D": ["2016", "2017"], "Model X AWD - 90D": ["2016", "2017"], "Model 3 Long Range  AWD Performance": ["2018"], "Model S 75D": ["2018", "2019"], "Model S P100D": ["2018", "2019"], "Model X Long Range": ["2019"], "Model S (85 kW-hr battery pack)": ["2013", "2014", "2015", "2016"], "Model S AWD - P85D": ["2015", "2016"], "Model X P100D": ["2018", "2019"], "Model S Performance (21in Wheels)": ["2019"], "Model X Performance (22in Wheels)": ["2019"], "Model S": ["2012"], "Model 3 Standard Range Plus": ["2019"], "Model 3 Long Range": ["2017", "2018", "2019"], "Model S 75kWh": ["2018"], "Model S Performance (19in Wheels)": ["2019"], "Model S (75 kW-hr battery pack)": ["2016", "2017"], "Model 3 Standard Range": ["2019"], "Model S AWD - 70D": ["2015", "2016"], "Model S (40 kW-hr battery pack)": ["2013"], "Model X AWD - 75D": ["2016", "2017"], "Model X AWD - 60D": ["2016", "2017"], "Model S (70 kW-hr battery pack)": ["2016"], "Model S AWD - 100D": ["2017"], "Model S (60 kW-hr battery pack)": ["2013", "2014", "2015", "2016", "2017"], "Model S (90 kW-hr battery pack)": ["2015", "2016"], "Model 3 Long Range  AWD": ["2018"], "Model X AWD - 100D": ["2017"], "Model S AWD - 90D": ["2015", "2016", "2017"], "Model 3 Mid Range": ["2018", "2019"], "Model S AWD - 75D": ["2016", "2017"], "Model 3 Long Range AWD": ["2019"], "Model X AWD - P90D": ["2016", "2017"], "Model S Standard Range": ["2019"], "Model S AWD - 85D": ["2015", "2016"], "Model S Long Range": ["2019"], "Model 3 Long Range AWD Performance": ["2019"]}